{
    "id": "2157928059",
    "url": "https://music.163.com/song?id=2157928059",
    "name": "先说谎的人 (苍白的话语动感版)",
    "artist list": [
        "DJ阿智",
        "DJ阿布"
    ],
    "artist id list": [
        "58149097",
        "58160751"
    ],
    "lyrics": "作词 : h3R3\n作曲 : h3R3\n原唱 : h3R3\n女声 : 张鑫\nDJ制作 : DJ阿智\n制作团队 : Lime Music Studio\ngirl\n我还欠你一句sorry\n遗留下的亏欠还在梦里\n泪水落在你的脸上\n让我的敷衍变得透明\n霓虹映射的倒影\n你被泪浸湿的侧脸\n逐渐占领我的思绪\n慢慢分裂破碎在每个角落\n对自己说就算了算了但梦还在不断提醒着\n那些我曾对你承诺的所有\n隐藏在黑夜中把我吞没\n苍白的话语刺痛着耳朵\n你说的挽留却不如谎言般生动\n也许我们在另一个时空\n被爱的那个人是我\n先说谎的那个人是我\n你成为我再也好不了的伤疤\n罪恶感却在无限生长\n那些我对你说过的谎话\n变成血液在我身体肆意流淌\n酒精反而让我清醒\n仿佛在我身边的是你\n我甚至嫉妒你身边的空气\n怎么才能让我从这循环抽离\n你的笑 你的泪 你的气味 你的模样\n成为枷锁留在回忆将我捆绑\n我说的谎 犯的错 我的懦弱 我的敷衍\n全都变成烙印刻在我身上\n如果你没放开我的手\n如果能够挽回我的错\n如果你能将时间倒流\n苍白的话语刺痛着耳朵\n你说的挽留却不如谎言般生动\n也许我们在另一个时空\n被爱的那个人是我\n先说谎的那个人是我\n\n收起"
}