{
    "id": "417859631",
    "url": "https://music.163.com/song?id=417859631",
    "name": "我好像在哪见过你",
    "alias": "动画电影《精灵王座》主题曲",
    "artist list": [
        "薛之谦"
    ],
    "artist id list": [
        "5781"
    ],
    "lyrics": "作词 : 薛之谦\n作曲 : 薛之谦\n编曲 : 周以力\n和你有关观后无感\n若是真的敢问作者何来罪恶\n劝人离散有多为难\n若美丽的故事来得太晚\n\n所以到哪里都像快乐被燃起\n就好像你曾在我隔壁的班级\n人们把难言的爱都埋入土壤里\n袖手旁观着别人尽力撇清自己\n\n我听见了你的声音\n也藏着颗不敢见的心\n我躲进挑剔的人群\n夜一深就找那颗星星\n\n我以为旅人将我热情都燃尽\n你却像一张情书感觉很初级\n人们把晚来的爱都锁在密码里\n字正腔圆的演说撇清所有关系\n\n我听见了你的声音\n也藏着颗不敢见的心\n我躲进挑剔的人群\n夜一深就找那颗星星\n你听不到我的声音\n怕脱口而出是你姓名\n像确定我要遇见你\n就像曾经交换过眼睛\n\n我好像在哪见过你\n我好像在哪见过你\n我好像在哪见过你\n我在劝我该忘了你\n\n制作人 : 薛之谦\n编曲 : 周以力\n吉他 : 张凇\n鼓 : 陈志昆\n大提琴 : 吴牧\n录音/混音 : 鲍锐\n录音助理 : 王晓海\n收起"
}