{
    "id": "2630594930",
    "url": "https://music.163.com/song?id=2630594930",
    "name": "牵丝戏",
    "alias": "DJ阿布Remix",
    "artist list": [
        "DJ阿布"
    ],
    "artist id list": [
        "58160751"
    ],
    "lyrics": "嘲笑谁恃美扬威\n没了心如何相配\n盘铃声清脆\n帷幕间灯火幽微\n我和你最天生一对\n没了你才算原罪\n没了心才好相配\n你褴褛我彩绘\n并肩行过山与水\n你憔悴我替你明媚\n是你吻开笔墨\n染我眼角珠泪\n演离合相遇悲喜为谁\n他们迂回误会\n我却只由你支配\n兰花指捻红尘似水\n三尺红台万事入歌吹\n唱别久悲不成悲\n十分红处竟成灰\n愿谁记得谁最好的年岁\n你一牵我舞如飞\n你一引我懂进退\n苦乐都跟随\n举手投足不违背\n将谦卑温柔成绝对\n你错我不肯对\n你懵懂我蒙昧\n心火怎甘心扬汤止沸\n你枯我不曾萎\n你倦我也不敢累\n用什么暖你一千岁\n风雪依稀秋白发尾\n灯火葳蕤揉皱你眼眉\n假如你舍一滴泪\n假如老去我能陪\n烟波里成灰也去得完美\n风雪依稀秋白发尾\n灯火葳蕤揉皱你眼眉\n假如你舍一滴泪\n假如老去我能陪\n烟波里成灰也去得完美\n收起"
}