{
    "id": "428375722",
    "url": "https://music.163.com/song?id=428375722",
    "name": "不说",
    "alias": "电影《从你的全世界路过》路过版主题曲",
    "artist list": [
        "李荣浩"
    ],
    "artist id list": [
        "4292"
    ],
    "lyrics": "编曲 : 李荣浩\n作词 : 黄伟文\n作曲 : 李荣浩\n制作人 : 李荣浩\n为了什么 男人的冰箱 总放着甜点\n为了什么 新娘都没有 为婚礼存钱\n怕你突然出现\n为了什么 有过去的人 会相信明天\n为了什么 该哭的场面 还亮出笑脸\n还当分手是种锻炼\n我不是不伤不痛不难过\n我只是不美不好都不说\n人说心如刀割\n钻石要琢磨\n感谢那些人擦过刮过\n帮我苦难修成正果\n品尝过的失落\n消化成温暖情歌\n等着你伤心时候点播\n我好像没心没肺话很多\n我只是不满不足都不说\n人说心如刀割\n钻石要琢磨\n感谢那些人擦过刮过\n生活才有更美轮廓\n干了每滴寂寞\n进化成更好的我\n等着你在我世界路过\n人说心如刀割\n钻石要琢磨\n感谢那些人擦过刮过\n生活才有更美轮廓\n干了每滴寂寞\n进化成更好的我\n等着你在我世界路过\n\n收起"
}