{
    "id": "191278",
    "url": "https://music.163.com/song?id=191278",
    "name": "最美的太阳",
    "artist list": [
        "张杰"
    ],
    "artist id list": [
        "6472"
    ],
    "lyrics": "作词 : 刘迦宁\n作曲 : 刘迦宁\n编曲 : 周治平\n\n我的世界\n因为有你才会美\n我的天空\n因为有你不会黑\n给我快乐\n为我伤心流眼泪\n给我宽容\n让我能展翅高飞\n你的话你的泪\n你的笑你的美\n在我眼中胜过最美的玫瑰\n抱着梦 往前飞\n不逃避 不后退\n你是我成功路上的堡垒\n给我翅膀\n让我可以翱翔\n给我力量\n是你让我变坚强\n不怕受伤\n因为有你在身旁\n你的笑 你的泪\n是我筑梦路上最美的太阳\n\n你的话你的泪\n你的笑你的美\n在我眼中胜过最美的玫瑰\n抱着梦 往前飞\n不逃避 不后退\n你是我成功路上的堡垒\n给我翅膀\n让我可以翱翔\n给我力量\n是你让我变坚强\n不怕受伤\n因为有你在身旁\n你的笑 你的泪\n是我筑梦路上最美的太阳\n给我翅膀\n让我可以翱翔\n给我力量\n是你让我变坚强\n不怕受伤\n因为有你在身旁\n你的笑 你的泪\n是我筑梦路上最美的太阳\n是我筑梦路上最美的太阳\n收起"
}