{
    "id": "1881471389",
    "url": "https://music.163.com/song?id=1881471389",
    "name": "瓮",
    "artist list": [
        "葛东琪",
        "张含韵"
    ],
    "artist id list": [
        "12136078",
        "10583"
    ],
    "lyrics": "作词 : 葛东琪\n作曲 : 葛东琪\n编曲 : 葛东琪\n制作人 : 葛东琪\n混音/母带 : 葛东琪\n被宽慰的期限还是没能作祟\n数不尽的落叶赞成季节收尾\n风雨下的情节一人一份单独够表现\n\n是无心的期许还是一种虚伪\n危在旦夕的云轻妆它的戒备\n被垒砌的情节承让温室的气候表现\n\n降降尘烟还是东流水\n大是大非够相依相偎\n呛呛耳边什么藉口登对\n谁先脱离危险\n\n散却的风不留花香味\n散却鸳鸯把爱恨归结\n只怪破的苍穹亵渎人间\n忌口下的箴言\n\n数不尽的落叶赞成季节收尾\n风雨下的情节一人一份单独够表现\n\n是无心的期许还是一种虚伪\n危在旦夕的云轻妆它的戒备\n被垒砌的情节承让温室的气候表现\n\n降降尘烟还是东流水\n大是大非够相依相偎\n呛呛耳边什么藉口登对\n谁先脱离危险\n\n散却的风不留花香味\n散却鸳鸯把爱恨归结\n只怪破的苍穹亵渎人间\n忌口下的箴言\n\n多危险\n就这种感觉很危险\n是于情于理的危险\n是谁先脱离的危险\n\n多危险\n就这种感觉很危险\n是于情于理的危险\n是谁先脱离的危险\n企划：牛雪吟/刘畅\n统筹：郭莹\n艺人统筹：傅凯/黄路欢\n收起"
}