{
    "id": "2716517317",
    "url": "https://music.163.com/song?id=2716517317",
    "name": "梦痛",
    "artist list": [
        "Happer",
        "Rezey",
        "Enlin00"
    ],
    "artist id list": [
        "58203900",
        "36289589",
        "51498273"
    ],
    "lyrics": "作词 : Happer/Rezey/花旦/柴文清\n作曲 : Happer/Rezey/花旦/柴文清\n编曲 : FRESH_ye\n\n时间把这感情熄灭\n黑色的琴键\n空洞的想念\n还没说完想说的告别\n你就已经走远\n爱教会我们许多\n太固执\n不愿在你的回忆里\n像傻子\n誓言像微风般 划过\n在指缝间逃脱\n是我 想的太多 才总是爱错\n\n时间总让人猝不及防\n还没来的及和你道个别\n离开你后我也变的迷茫\n你变成我心里最大的结\n对你的滤镜\n在我的心里没改变\n可你我的剧情\n却变成幻想的相反面\n我以为慢慢的爱\n会让你慢慢的爱上我\n可你的一切举动\n显得轻松\n慢慢变冷落\n我希望有你在\n但也没有法控制你离开\n我焦急的等待\n度过这个无人的tonight\n当通话变成了骚扰当思念都变成了视奸\n我的心早被困在这痛苦和挣扎之间\n只怪内心还保留那份我 对你的执念\n我没想到你我的感情最后败给了时间\n短暂的痛苦 冲突\n慢慢和现实融入\n皱眉头在梦中\n失败在不断重复\n你的笑脸 太耀眼\n在逼迫着我成熟\n我会牢牢的记住你最后对我的叮嘱\n\n这梦醒太痛\n不敢再触碰\n我的在意 你的沉默\n被泪水淹没\n我还是 不肯走\n你给的 爱太重\n把我给 深深囚禁 在这回忆 中\n没关系 我爱你\n所以我听\n对不起 我爱你\n像呼吸\n\n蝴蝶飞不过沧海 飞不回相爱的那天\n曾经我给你买的戒指 被你脱落手指尖\n你留下最深的回忆 就是你离开的画面\n你带走所有的真心 只剩下褪色的照片\n习惯了看你朋友圈 习惯了深夜掉眼泪\n习惯了有你在身边 习惯做爱情的点缀\n习惯了万丈的深渊 习惯被黑夜给碾碎\n习惯你留在我心间 习惯你身上的香味\n最远的距离不是没了人爱 是熟悉变陌生\n这段悲伤的故事 给我留了空洞的眼神\n可能是错误的时间相遇 可能我们没缘分\n在这个感情泛滥的时代 只能怪我太认真\n光阴给她披上了滤镜 没看清包裹的真心\n我备忘录里全是你曾经 给我发过的语音\n我知道 已经没有结果了 但回忆攥在了手心\n深夜都是靠着安眠药 和一些麻木的酒精\n\n和声Backing Vocal : SJoK\n混音&母带Mixing&Mastering : 李鹿亦\n统筹 Coordination : 米兔/马畅远\n营销 Promotion : 曹海林/朱贯松\n支持 Project Assistant : 曲泓宇\n词曲协力Lyrics and music assistant : pp\n设计 Visual Designer : 柠檬\n监制Executive Producer : 丁柏昕\n发行统筹 Publishing Manager : 张甜甜\n出品人 Publisher : 袁晓童\n音乐发行 Publishing : 索尼音乐\nOP : 杭州雪球音乐有限公司\n收起"
}