{
    "id": "2156229828",
    "url": "https://music.163.com/song?id=2156229828",
    "name": "蝴蝶效应",
    "alias": "Butterfly",
    "artist list": [
        "TizzyT",
        "LEGGO",
        "CHOCKEY有三",
        "Crazy C",
        "HEAT J"
    ],
    "artist id list": [
        "1204010",
        "12293217",
        "36109845",
        "13796374",
        "12085631"
    ],
    "lyrics": "作词 : TizzyT/LEGGO/CHOCKEY有三/Crazy C/HEAT J\n作曲 : TizzyT/LEGGO/CHOCKEY有三/Crazy C/HEAT J\n编曲 : Dough-Boy/细GalaxyMan\n制作人 : TizzyT/Dough-Boy\nLEGGO：\nI got a feellinain't nobody can stop me right now\n这街道太吵甚至盖住了哀嚎\n蝴蝶煽动了翅膀掀起了海啸\n当你说 Wow\n听他们说 Wow\nCHOCKEY有三：\n我不想说话的时候会被其他人打断\n帅的永远都帅不需要整容和打扮\n困住我的不是想法是生活的牵绊\n现在有太多人想要在我身上打算盘\n我插上耳机因为这个世界太吵\n我身边都是 Young Blood我才不怕衰老\n当生活像个笼子困住了太多菜鸟\n又何尝不是挖到深处我才懂得开窍\n像蝴蝶一样挥动翅膀就能掀起风波\n沟通不需要键盘我有我专属的动作\n这一百秒的综艺根本不够我去诉说\n我的宿命是在舞台而不是在写字楼\nWow～\nCrazyC：\n当所有人都怀疑你时你眼神该往哪看\n我的目光依旧坚定嘴里唱的没有打断\n从学校出来做音乐没想过太多打算\n我选择的是否正确在音轨里找答案\n我像蝴蝶扇动翅膀拍打无数个黑夜\n一次次许下愿望再把蜡烛给吹灭\n麦克风陪我在出租房里度过了3 years\n我真的太说唱了所以我连裤裆都 Lay back\n我像狮子咬着猎物没有一点点松动\n我说的热爱是我听见鼓点就有一种冲动\n我的韵脚太辣让你们一次呛个够\n“这一刻我等了7年”还在做一样的梦\nLEGGO：\nI got a feellinain't nobody can stop me right now\n这街道太吵甚至盖住了哀嚎\n蝴蝶煽动了翅膀掀起了海啸\n当你说 Wow\n听他们说 Wow\nHEAT J：\nYeah在巡演路上试过三天只睡两个钟\n事情太多想把自己掰成两个用\n想个说辞这一切要怎么讲的通\n回头才发现原来是我一直想的梦\n流言蜚语带给我的不止疼\n到底该怎么写你才信我的故事真\n我不停 Push绝不仅是为了物质\n吃好几年的快餐现在我想起来就肚子疼\nI cant feel no pain\nCuz the pain inside my vain\n我不是为了钱\n能买到的都不值钱\n我只想留下我的脚步在离开之前\n能证明的只有时间\nTizzyT：\n那帮 Rapper太饿了现在都想要吃人\n对着镜头说谎话他们都假装斯文\n新说唱爱奇艺你管他资不资本\n这个文化我已经分不清是爱是恨\n我没有忘记跟我兄弟街上做的那些勾当\n如果我没钱开饭我比你还要抽象\n我的人生都在“ Freestyle”你叫我怎“ Hold on”\n如果你打不死我就骑在你的头上\n音乐节到夜店你看他的头一直晃\nM12的牛排黑松露搭配鱼子酱\n快抬起头告诉他们你这一路的跌宕\n你可以忘词但别忘了你是来自街上\nLEGGO：\nI got a feellinain't nobody can stop me right now\n这街道太吵甚至盖住了哀嚎\n蝴蝶煽动了翅膀掀起了海啸\n当你说 Wow\n听他们说 Wow\n录音工程 : TizzyT/林岳彰@宇宙电台Universe Studio\n音频编辑 : HEAT J/细GalaxyMan\n混音工程：细GalaxyMan\n母带处理：周天澈@Studio21A\n收起"
}