{
    "id": "1861116288",
    "url": "https://music.163.com/song?id=1861116288",
    "name": "曾幸福 cang hang fuk",
    "artist list": [
        "曾舜晞"
    ],
    "artist id list": [
        "12008056"
    ],
    "lyrics": "作词 : 三本目\n作曲 : 赵广为\n编曲 : 李昕达\n心情 蒙着眼睛\n就似 灰暗的雾\n心潮 燃着晚灯\n但 借不到温度\n忘掉了 呼吸 亦好\n在我心里 刻记号\n落下了的雨 流光里 像飞舞\n来让我 将这记忆\n邮寄 在光阴 散落 人海\n慢放了心跳 望向 天空\n还有 温暖 霞浪 色彩\n来让我 收起耳朵\n时间静了 抹去 一切 忆记\n在扑空 的手臂内\n曾幸福 一起旅行 不过意外\n心情 流浪 也好\n觅到 归去的路\n煎熬 长夜 会好\n像 某一次感冒\n云渐散 轻轻 问好\n若有 经过 的爱慕\n梦呓中 记住 人生里的拥抱\n来让我 将这记忆\n邮寄 在光阴 散落 人海\n慢放了心跳 望向 天空\n还有 温暖 霞浪 色彩\n来让我 收起耳朵\n时间静了 抹去 一切 忆记\n在扑空 的手臂内\n留下了 花火 证实 曾有爱\n\n心情 蒙着眼睛\n就似 灰暗的雾\n心潮 燃着了灯\n但 借不到温度\nOP : 好料策划\nSP : Warner Chappell Music Publishing Agency (Beijing) Ltd.\n录音 : 李昕达\n弦乐编写 : 李昕达\n弦乐 : 国际首席爱乐乐团\n吉他 : 高飞\n大提琴 : 郎莹\n伴唱编写 : 李昕达\n伴唱 : Class合唱团\n乐器录音棚 : 天舞IDG Music Studio\n混音 : 李昕达\n母带 : 李昕达/任允翔\n人声录音室 : KONG Studio\n人声录音 : 刘天鸿\n制作助理 : B1uewhiTe蓝白\n企划 : Studio JOSEPH\n出品 : Studio JOSEPH\n发行 : 北京掌上精彩科技有限公司\n收起"
}