{
    "id": "202376",
    "url": "https://music.163.com/song?id=202376",
    "name": "背影",
    "artist list": [
        "赵雷"
    ],
    "artist id list": [
        "6731"
    ],
    "lyrics": "作词 : 赵雷\n作曲 : 赵雷\n我们正需要一场瓢泼的雨\n来冲洗这旧日的不喜\n鸟儿都飞到房檐下的新巢\n淋湿的身影要归去哪里\n昨日是庆幸着 为何今日要感伤\n让烦恼都随雨流进下水道\n只是我不能抑制自己的感伤\n那就让我随波逐流去放荡\n天空很远 夕阳很近\n顺着那条小路是你回家的方向\n那个黄昏有最温馨的晚餐和慈祥的脸庞\n月亮入睡 在有星星下的路口\n那是迫不及待寻找已久的温柔\n那个有理想的青年是多么轻松和自由\n对留下的脚印 回头 挥挥手\n\n昨日是庆幸着 为何今日要感伤\n让烦恼都随雨流进下水道\n只是我不能抑制自己的感伤\n那就让我随波逐流去放荡\n天空很远 夕阳很近\n顺着那条小路是你回家的方向\n那个黄昏有最温馨的晚餐和慈祥的脸庞\n月亮入睡 在有星星下的路口\n那是迫不及待寻找已久的温柔\n那个有理想的青年是多么轻松和自由\n对留下的脚印 回头 挥挥手\n\n月亮入睡 在有星星下的路口\n那是迫不及待寻找已久的温柔\n那个有理想的青年是多么轻松和自由\n对留下的脚印 回头\n挥挥手\n\n收起"
}