{
    "id": "1414112302",
    "url": "https://music.163.com/song?id=1414112302",
    "name": "小时候的我们",
    "artist list": [
        "周兴哲"
    ],
    "artist id list": [
        "980025"
    ],
    "lyrics": "作词 : 周兴哲/吴易纬\n作曲 : 周兴哲\n在你遗忘的 小时候 我在等着\n调色盘装满了 宇宙的颜色 单纯狂热\n哭是直觉的 笑是发自真心的\n喜欢就拥抱着 没有复杂的 嫉妒猜测\n\n这些年 遍体鳞伤 你 不想认输了\n委屈求全 妥协 不得不做的选择\n最后得到了什么\n\n从哪一天开始 不后悔 跟爱的人争执\n势不两立地对峙 这样子\n承诺还有谁坚持\n\n「愿望 停止 开始」\n\n你追随的 渴望的 握在手里了\n怎么会 失去了 小时候的快乐 为什么\n你付出的 失去的 都成为你了\n要永远 相信着 小时候的我们 勇敢着\n\n在你遗忘的 小时候 我在等着\n调色盘装满了 宇宙的颜色 单纯狂热\n哭是直觉的 笑是发自真心的\n喜欢就拥抱着 没有复杂的 嫉妒猜测\n\n这些年 没有黯淡 你 眼神的光泽\n还有向往 就为自己任性地选择\n成为独一无二的\n\n还来得及开始 去追回 爱的人的消逝\n哪怕变成最固执 这样子\n承诺值得更坚持\n\n「愿望 重新 开始」\n\n你追随的 渴望的 握在手里了\n怎么会 失去了 小时候的快乐 为什么\n你付出的 失去的 都成为你了\n要永远 相信着 小时候的我们 勇敢着\n收起"
}