{
    "id": "1975802964",
    "url": "https://music.163.com/song?id=1975802964",
    "name": "头头是道 (LIVE版)",
    "artist list": [
        "艾热 AIR",
        "王以太"
    ],
    "artist id list": [
        "1203045",
        "12236125"
    ],
    "lyrics": "作词 : 艾热 AIR/王以太\n作曲 : 艾热 AIR/王以太\n编曲 : 雷十一/也是福\n作词：艾热 AIR/王以太\n作曲：艾热 AIR/王以太\n编曲：雷十一/也是福（ Eddie Beatz）\n音乐总监：刘佳 Zeus Production\n制作总监：卡斯\n混音：小武\n吉他：李嘉 Liam/雷十一\n贝斯：孟宇\n鼓手：刘一凡\n键盘：郑皓荣\n竹笛：张海亮/丁晓逵\n感情就像天气\n有时阴有时晴\n所有的喜和怒\n哀或乐都是你\n这次就怪我自己太不小心\n但下次 baby(宝贝)\n可真不一定\n感情就像天气\n有时阴有时晴\n所有的喜或怒\n哀或乐都是你\n这次就怪我自己太不小心\n但下次 baby(宝贝)\n可真不一定\n真不一定\nReady(准备)\n你说我现在就像外星异类\n一个眼神给你自己体会\n毒鸡汤有点伤我没慌\n但别生气就拿我跟谁比对\n你拿我跟谁比我都不输对\n就算输了我也绝对不服对\n我说我会像妈妈一样爱你\n我是真心的\n尽管爱\n我们都糊里糊涂\n明明你很了解我的为人\n请你别给自己留下泪痕\n我为刚才的冲动悔恨\n为什么会跳窗\n当幸福来推门\n嘴巴成了“核武器”\n辐射你和我的克制力\n不是早就说好了做自己\n怎么成为对相互的不服气\n最佳拍档成为对家\n挥砍着负能量\n击碎了我们的盔甲\n自顾自地说了好多废话\n就是无法说出抱歉\n请跟我回家\nHuman nature(人性)保护自尊心\n又或者只是焦虑犯神经\n原因是对彼此太沉迷\n所以免不了偶然的暴风雨\n感情就像天气\n有时阴有时晴\n所有的喜和怒\n哀或乐都是你\n这次就怪我自己太不小心\n但下次 baby(宝贝)\n可真不一定\n早上起床我先拉开窗帘\n你说你还没醒\n阳光未免太过刺眼\n晚上睡觉太累忘记关灯\n你又怪我粗心\n光线太亮会失眠\n每到点餐就会点随便\n土豆不脆\n又要流下你的眼泪\n关键时刻就没电\n叫我怎么选\n叫我怎么面对\n没法平息升级的抱怨\n一人一句听不进道歉\n有理有据谁都不回应\n不说话又被拉黑微信\n别再对我磨练你武功\n明明我的错误很普通\n吵架也请你轻轻\n不要用力误导爱彼此的心情\n没发现\n你的眼睛多了一点点火焰\n如果我能早点收敛\n就不用学消防员\n请别眨眼\n我爱你\n即使比谁的道理多\n我也理亏\n请你给我机会\n心里话想对你说\n感情就像天气\n有时阴有时晴\n所有的喜和怒\n哀或乐都是你\n这次就怪我自己太不小心\n但下次 baby宝贝\n可真不一定\nOne more time\n(再来一遍)\n感情就像天气\n有时阴有时晴\n所有的喜和怒\n哀或乐都是你\n这次就怪我自己太不小心\n但下次 baby(宝贝)\n可真不一定\nSolo独奏\nLadies and gentlemen solo\n(女士们先生们接下来是独奏)\n感情就像天气\n有时阴有时晴\n所有的喜和怒\n哀或乐都是你\n这次就怪我自己太不小心\n但下次 baby(宝贝)\n可真不一定\nEverybody(所有人)\n感情就像天气\n有时阴有时晴\n所有的喜和怒\n哀或乐都是你\n这次就怪我自己太不小心\n但下次 baby(宝贝)\n可真不一定\n但下次 baby(宝贝)\n但下次 baby(宝贝)\n但下次 baby(宝贝)\n可真不一定\nPGM：董海龙 Zeus Production/徐帅 Zeus Production/徐培霖 Zeus Production\nAuto- Tune：李雨杭 Yuu Zeus Production\n录音编辑：刘俊杰 Zeus Production/王濛 Zeus Production/小武\n收起"
}