{
    "id": "1995071414",
    "url": "https://music.163.com/song?id=1995071414",
    "name": "半边山半边海",
    "artist list": [
        "王铮亮",
        "陈楚生"
    ],
    "artist id list": [
        "5518",
        "2124"
    ],
    "lyrics": "作词 : 王铮亮/陈楚生\n作曲 : 王铮亮\n编曲 : 王铮亮/陈楚生\n制作人 : 王铮亮\n\n生：\n在半边山的海 海半边的山\n我在山与海之间\n亮：\n在我心中的你 你眼里的我\n牵挂着无数思念\n\n生：\n山 有小黄花做伴\n海 有小船停靠的岸\n亮：\n夜 里星星在眨眼\n人 又不觉的想念\n\n合：\n在半边山的海 喧嚣都不在\n静静听海浪道来\n爱是怎样的存在 几个笨小孩\n哭着笑着多开怀\n\n山 有小黄花做伴\n海 有小船停靠的岸\n夜 里星星在眨眼\n我 又看见你的脸\n\n人生总要历经悲与欢\n我们总会有相聚有散\n曾经陪伴的人已走远\n或许化作天上星星点点\n\n海上飘着一只小纸船\n山与海相依偎聊着天\n满山黄花望天空的蓝\n寄托我对你的思念\n\n啦~\n\n亮：\n山 有小黄花做伴\n生：\n海 有小船停靠的岸\n亮：\n夜 里星星在眨眼\n生：\n人 又不觉的\n合：\n想念\n制作：王铮亮\n编曲：王铮亮 陈楚生\n吉他：陈楚生\n手风琴：王铮亮\n收起"
}