{
    "id": "32358362",
    "url": "https://music.163.com/song?id=32358362",
    "name": "女孩",
    "alias": "电视剧《长不大的爸爸》片头曲",
    "artist list": [
        "韦礼安"
    ],
    "artist id list": [
        "5379"
    ],
    "lyrics": "作词 : 韦礼安\n作曲 : 韦礼安\n女孩不想看你受一样的伤害\n所以学会溺爱\n一而再再而再三而再的错怪\n到底要什么姿态\n才不会显得我在使坏\n来者不善善者不来\n因为我也曾经站在门外\n为了你上山下海为了你掏空口袋\n满足你眼神里的期待\n为了你不敢懈怠再累也伪装起来\n为了你眼神里的崇拜\n女孩我的故事因为你而展开\n为你学会忍耐为你坏习惯我都改\n女孩不想看你受一样的伤害\n所以学会溺爱错怪你真正要的爱\n为了你上山下海为了你掏空口袋\n满足你眼神里的期待\n为了你不敢懈怠再累也伪装起来\n为了你眼神里的崇拜\n女孩我的故事因为你而展开\n为你学会忍耐为你坏习惯我都改\n女孩不想看你受一样的伤害\n所以学会溺爱\n一而再再而再三而再的错怪\n你还需要我的胸怀（夜里哭泣像个小孩）\n你还一样是我的女孩（不用担心我随时都在）\n其实是我还需要你对我依赖\n女孩我的故事因为你而展开\n为你学会忍耐为你坏习惯我都改\n女孩不想看你受一样的伤害\n所以学会溺爱\n一而再再而再三而再的错怪\n请原谅我不想那么快和你分开\n一而再再而再三而再的\n什么才是你真正要的\n请原谅我不想要\n那么快就和你分开\n收起"
}