{
    "id": "26145111",
    "url": "https://music.163.com/song?id=26145111",
    "name": "虐心",
    "artist list": [
        "徐良",
        "孙羽幽"
    ],
    "artist id list": [
        "5929",
        "1049025"
    ],
    "lyrics": "作词 : 徐良\n作曲 : 徐良\n编曲 : 颜小健\n落叶飘过一个曾经\n曾经许下一个约定\n两个人的手深深握紧\n同样的街景\n熟悉的声音\n你说了对不起\n男：坚强从来都是故意\n故意假装着不在意\n亲爱的请你不要哭泣\n只要你幸福\n我愿意忘记\n记忆中全部的你\n女：下一次我们会在\n某个路口相遇\n请告诉我你过得很开心\n想念你的眼睛\n你的表情 你的身影\n泪湿在一个人的夜里\n男：下一次我们会\n在某个路口相遇\n请告诉我怎么能不想你\n忘掉你的真心\n你的用心你的伤心\n忘掉牵挂着你的自己\n和尘封的记忆\n女：落叶飘过一个曾经\n曾经许下一个约定\n两个人的手深深握紧\n同样的街景\n熟悉的声音\n你说了对不起\n男：坚强从来都是故意\n故意假装着不在意\n亲爱的请你不要哭泣\n只要你幸福\n我愿意忘记\n记忆中全部的你\n女：下一次我们会\n在某个路口相遇\n请告诉我你过得很开心\n想念你的眼睛\n你的表情 你的身影\n泪湿在一个人的夜里\n男：下一次我们会\n在某个路口相遇\n请告诉我\n怎么能不想你\n忘掉你的真心\n你的用心 你的伤心\n合：忘掉牵挂着你的自己\n女：下一次我们会\n在某个路口相遇\n请告诉我你过得很开心\n想念你的眼睛\n你的表情 你的身影\n泪湿在一个人的夜里\n合：下一次我们会\n在某个路口相遇\n请告诉我怎么能不想你\n忘掉你的真心\n你的用心 你的伤心\n忘掉牵挂着你的自己\n女：和尘封的记忆\n收起"
}